<?xml version="1.0" encoding="UTF-8"?>
<!DOCTYPE config SYSTEM "config.dtd">
<panels>
	<panel>
		<properties>
			<property name="size" value="28"/>
			<property name="monitor" value="0"/>
			<property name="screen-position" value="2"/>
			<property name="fullwidth" value="1"/>
			<property name="xoffset" value="0"/>
			<property name="yoffset" value="0"/>
			<property name="handlestyle" value="0"/>
			<property name="autohide" value="0"/>
			<property name="transparency" value="20"/>
			<property name="activetrans" value="0"/>
		</properties>
		<items>
			<item name="xfce4-menu" id="5"/>
			<item name="separator" id="6"/>
			<item name="places" id="127248543510"/>
			<item name="tasklist" id="3"/>
			<item name="systray" id="4"/>
			<item name="pager" id="2"/>
			<item name="showdesktop" id="1"/>
			<item name="separator" id="11"/>
			<item name="clock" id="14"/>
			<item name="separator" id="13"/>
			<item name="actions" id="12"/>
		</items>
	</panel>
	<panel>
		<properties>
			<property name="size" value="40"/>
			<property name="monitor" value="0"/>
			<property name="screen-position" value="11"/>
			<property name="fullwidth" value="0"/>
			<property name="xoffset" value="307"/>
			<property name="yoffset" value="727"/>
			<property name="handlestyle" value="0"/>
			<property name="autohide" value="0"/>
			<property name="transparency" value="21"/>
			<property name="activetrans" value="0"/>
		</properties>
		<items>
			<item name="launcher" id="12724841280"/>
			<item name="launcher" id="12724848942"/>
			<item name="launcher" id="12724852689"/>
			<item name="launcher" id="12724849554"/>
			<item name="launcher" id="12730544370"/>
			<item name="launcher" id="12724849353"/>
			<item name="launcher" id="12724849966"/>
			<item name="launcher" id="12730708740"/>
			<item name="launcher" id="12724849685"/>
			<item name="launcher" id="12724851048"/>
			<item name="iconbox" id="12724847470"/>
		</items>
	</panel>
</panels>
